{"is_source_file": true, "format": "JavaScript", "description": "This file defines utility functions and constants for a Tic-Tac-Toe game, including functions to determine the winner and check for a draw based on the game board state.", "external_files": [], "external_methods": [], "published": ["calculateWinner", "isDraw", "lines"], "classes": [], "methods": [{"name": "calculateWinner(board)", "description": "Checks the game board to determine if either player 'X' or 'O' has won, returning the winner's symbol or null if there is no winner.", "scope": "", "scopeKind": ""}, {"name": "isDraw(board)", "description": "Checks if the game has ended in a draw, i.e., the board is full and there is no winner.", "scope": "", "scopeKind": ""}], "calls": ["calculateWinner(board)"], "search-terms": ["tic-tac-toe", "calculateWinner", "isDraw", "LINES", "game logic", "board evaluation", "game utility functions"], "state": 2, "file_id": 17, "knowledge_revision": 39, "git_revision": "6948101aba8c9ab05bf8bfb081ee132653872134", "ctags": [{"_type": "tag", "name": "LINES", "path": "/home/kavia/workspace/code-generation/tic-tac-toe-classic-221777-221786/tic_tac_toe_frontend/src/utils/game.js", "pattern": "/^const LINES = [$/", "language": "JavaScript", "kind": "constant"}, {"_type": "tag", "name": "calculateWinner", "path": "/home/kavia/workspace/code-generation/tic-tac-toe-classic-221777-221786/tic_tac_toe_frontend/src/utils/game.js", "pattern": "/^function calculateWinner(board) {$/", "language": "JavaScript", "kind": "function", "signature": "(board)"}, {"_type": "tag", "name": "isDraw", "path": "/home/kavia/workspace/code-generation/tic-tac-toe-classic-221777-221786/tic_tac_toe_frontend/src/utils/game.js", "pattern": "/^function isDraw(board) {$/", "language": "JavaScript", "kind": "function", "signature": "(board)"}], "hash": "b92f4a7ca54bd7b40db9ec539b5c1829", "format-version": 4, "code-base-name": "tic_tac_toe_frontend", "filename": "tic_tac_toe_frontend/src/utils/game.js", "revision_history": [{"39": "6948101aba8c9ab05bf8bfb081ee132653872134"}]}